{
  "users": [
    {
      "email": "ds2q88@gmail.com",
      "username": "moon",
      "password": "moon",
      "id": 1
    },
    {
      "email": "bloop@gmail.com",
      "username": "bloop",
      "password": "bloop",
      "id": 2
    },
    {
      "email": "a@a.com",
      "username": "a",
      "password": "a",
      "id": 3
    },
    {
      "email": "bloop@bloop.com",
      "username": "blaap",
      "password": "bleep",
      "id": 4
    },
    {
      "email": "g@g.com",
      "username": "aa",
      "password": "a",
      "id": 5
    },
    {
      "email": "a@ab.com",
      "username": "meow",
      "password": "meow",
      "id": 6
    },
    {
      "email": "meow1",
      "username": "meow1",
      "password": "meow1",
      "id": 7
    },
    {
      "email": "fakiewakie@asdf.com",
      "username": "joden",
      "password": "asdf",
      "id": 8
    },
    {
      "email": "laurenbmoon@gmail.com",
      "username": "moonmoon",
      "password": "sciip",
      "id": 9
    },
    {
      "email": "",
      "username": "",
      "password": "",
      "id": 10
    },
    {
      "email": "johnnathanwood@gmail.com",
      "username": "1",
      "password": "1",
      "id": 11
    },
    {
      "email": "fakeemail@fake.com",
      "username": "fakeyfake",
      "password": "yeet",
      "id": 12
    },
    {
      "email": "austin.gorman@gmail.com",
      "username": "dingdong69",
      "password": "d4nny",
      "id": 13
    },
    {
      "email": "brett@brett.com",
      "username": "brett",
      "password": "brett",
      "id": 14
    },
    {
      "email": "elusky@live.com",
      "username": "urbutt",
      "password": "butts43va",
      "id": 15
    },
    {
      "email": "al@me.com",
      "username": "al",
      "password": "al",
      "id": 16
    },
    {
      "email": "meg@me.me",
      "username": "megducharme",
      "password": "12345",
      "id": 17
    },
    {
      "email": "jenna@j.com",
      "username": "jennabsol",
      "password": "1234",
      "id": 18
    },
    {
      "email": "poo",
      "username": "moonl",
      "password": "hun",
      "id": 19
    },
    {
      "email": "jenniferlawson000@gmail.com",
      "username": "janjan",
      "password": "janjan",
      "id": 20
    },
    {
      "email": "lauren.moon@gmail.com",
      "username": "banksmoon",
      "password": "hephalumps",
      "id": 21
    },
    {
      "email": "meg@ducharme.com",
      "username": "megducharme13",
      "password": "12345",
      "id": 22
    },
    {
      "email": "tito",
      "username": "tito",
      "password": "tito",
      "id": 23
    },
    {
      "email": "dingdong69@gmail.com",
      "username": "dingdong420",
      "password": "password",
      "id": 24
    },
    {
      "email": "mkonabik@gmail.com",
      "username": "matt",
      "password": "none",
      "id": 25
    }
  ],
  "establishments": [
    {
      "id": 1,
      "name": "Taquería El Amigo José",
      "address": "2198 Nolensville Pike, Nashville, TN 37211",
      "hours": "shit",
      "phoneNumber": "(615) 606-5334",
      "description": "Delicious food truck with many options. It has a small outside seating area for visitors. Two grills keep the area smelling delicious",
      "establishmentTypeID": 2,
      "beer": "No",
      "liquor": "No",
      "mixDrinks": "No",
      "freeSalsa": "No",
      "PaymentTypeID": 1,
      "foodPoints": 28,
      "tacoPoints": 8,
      "margaritaPoints": 9,
      "quesoPoints": 6,
      "burritoPoints": 1,
      "salsaPoints": 1
    },
    {
      "id": 2,
      "name": "Restaurante El Paraiso",
      "address": "2209 Nolensville Pike, Nashville, TN 37211",
      "hours": "shit",
      "phoneNumber": "(615) 290-7608",
      "description": "Classic hispanic food located convenienetly next to 440. Come have a drink instead of being traffic",
      "establishmentTypeID": 1,
      "beer": "Yes",
      "liquor": "Yes",
      "mixDrinks": "Yes",
      "freeSalsa": "Yes",
      "PaymentTypeID": 3,
      "foodPoints": 15,
      "tacoPoints": 17,
      "margaritaPoints": 3,
      "quesoPoints": 1,
      "burritoPoints": 6,
      "salsaPoints": 18
    },
    {
      "id": 3,
      "name": "La Fondita Express",
      "address": "2442 Nolensville Pike, Nashville, TN 37211",
      "hours": "shit",
      "phoneNumber": "(615) 290-7840",
      "description": "Fresh food, made quick! try our sauces",
      "establishmentTypeID": 2,
      "beer": "No",
      "liquor": "No",
      "mixDrinks": "No",
      "freeSalsa": "No",
      "PaymentTypeID": 1,
      "foodPoints": 1,
      "tacoPoints": 9,
      "margaritaPoints": 9,
      "quesoPoints": 47,
      "burritoPoints": 0,
      "salsaPoints": 1
    },
    {
      "id": 4,
      "name": "Delicias Las Catrachas",
      "address": "2518 Nolensville Pike, Nashville, TN 37211",
      "hours": "shit",
      "phoneNumber": "(615) 686-5783",
      "description": "Authentic delicious Honduran food!",
      "establishmentTypeID": 1,
      "beer": "Yes",
      "liquor": "Yes",
      "mixDrinks": "Yes",
      "freeSalsa": "Yes",
      "PaymentTypeID": 3,
      "foodPoints": 5,
      "tacoPoints": 2,
      "margaritaPoints": 8,
      "quesoPoints": 0,
      "burritoPoints": 16,
      "salsaPoints": 0
    },
    {
      "id": 5,
      "name": "Nashville Venezuela Food",
      "address": "2244, 2604 Nolensville Pike suite a, Nashville, TN 37211",
      "hours": "shit",
      "phoneNumber": "(615) 891-4616",
      "description": "Authentic delicious Venezuelan food!",
      "establishmentTypeID": 1,
      "beer": "Yes",
      "liquor": "Yes",
      "mixDrinks": "Yes",
      "freeSalsa": "Yes",
      "PaymentTypeID": 3,
      "foodPoints": 2,
      "tacoPoints": 7,
      "margaritaPoints": 2,
      "quesoPoints": 6,
      "burritoPoints": 7,
      "salsaPoints": 0,
      "burittoPoints": 1
    },
    {
      "id": 6,
      "name": "La Hacienda Taqueria",
      "address": "2615 Nolensville Pike, Nashville, TN 37211",
      "hours": "shit",
      "phoneNumber": "(615) 256-6142",
      "description": "Good food. Great margaritas. Obama ate here!",
      "establishmentTypeID": 1,
      "beer": "Yes",
      "liquor": "Yes",
      "mixDrinks": "Yes",
      "freeSalsa": "Yes",
      "PaymentTypeID": 3,
      "foodPoints": 30,
      "tacoPoints": -1,
      "margaritaPoints": 4,
      "quesoPoints": 6,
      "burritoPoints": 0,
      "salsaPoints": 2
    },
    {
      "id": 7,
      "name": "Taqueria San Luis",
      "address": "2624 Nolensville Pike, Nashville, TN 37211",
      "hours": "shit",
      "phoneNumber": "(615) 254-1010",
      "description": "Quick food at the food truck!",
      "establishmentTypeID": 2,
      "beer": "No",
      "liquor": "No",
      "mixDrinks": "No",
      "freeSalsa": "No",
      "PaymentTypeID": 1,
      "foodPoints": 3,
      "tacoPoints": 6,
      "margaritaPoints": 8,
      "quesoPoints": 7,
      "burritoPoints": 6,
      "salsaPoints": 6
    },
    {
      "id": 8,
      "name": "Taqueria Aguilar Food Truck",
      "address": "230 Thompson Ln, Nashville, TN 37211",
      "hours": "shit",
      "phoneNumber": "(615) 319-8795",
      "description": "Food that is tasty, very fast. Call and order ahead!",
      "establishmentTypeID": 2,
      "beer": "No",
      "liquor": "No",
      "mixDrinks": "No",
      "freeSalsa": "No",
      "PaymentTypeID": 1,
      "foodPoints": 4,
      "tacoPoints": 11,
      "margaritaPoints": 6,
      "quesoPoints": 6,
      "burritoPoints": 9,
      "salsaPoints": 15
    },
    {
      "id": 9,
      "name": "Carniceria Y Taqueria Don Juan",
      "address": "2910 Nolensville Pike, Nashville, TN 37211",
      "hours": "shit",
      "phoneNumber": "(615) 833-1690",
      "description": "Drive through tacos! We have outside seating",
      "establishmentTypeID": 2,
      "beer": "Yes",
      "liquor": "No",
      "mixDrinks": "No",
      "freeSalsa": "No",
      "PaymentTypeID": 3,
      "foodPoints": 9,
      "tacoPoints": 14,
      "margaritaPoints": 25,
      "quesoPoints": 7,
      "burritoPoints": 1,
      "salsaPoints": 24
    },
    {
      "id": 10,
      "name": "Pupuseria Reina",
      "address": "3003 Nolensville Pike, Nashville, TN 37211",
      "hours": "shit",
      "phoneNumber": "(615) 243-8425",
      "description": "Family run Establishment! Reasonable prices. Above average hispanic food",
      "establishmentTypeID": 1,
      "beer": "Yes",
      "liquor": "Yes",
      "mixDrinks": "Yes",
      "freeSalsa": "Yes",
      "PaymentTypeID": 3,
      "foodPoints": 34,
      "tacoPoints": 66,
      "margaritaPoints": 46,
      "quesoPoints": 22,
      "burritoPoints": 1,
      "salsaPoints": -1
    },
    {
      "id": 11,
      "name": "Taqueria El Dolar",
      "address": "3500 Nolensville Pike, Nashville, TN 37211",
      "hours": "shit",
      "phoneNumber": "(770) 375-6817",
      "description": "A chain for a reason. Come try the tacos!",
      "establishmentTypeID": 2,
      "beer": "No",
      "liquor": "No",
      "mixDrinks": "No",
      "freeSalsa": "No",
      "PaymentTypeID": 3,
      "foodPoints": 113,
      "tacoPoints": 11,
      "margaritaPoints": 54,
      "quesoPoints": 12,
      "burritoPoints": 23,
      "salsaPoints": 7
    },
    {
      "id": 12,
      "name": "El Tapatio",
      "address": "3611 Nolensville Pike, Nashville, TN 37211",
      "hours": "shit",
      "phoneNumber": "(615) 445-7781",
      "description": "We claim to be the best for a reason!",
      "establishmentTypeID": 1,
      "beer": "Yes",
      "liquor": "No",
      "mixDrinks": "No",
      "freeSalsa": "Yes",
      "PaymentTypeID": 3,
      "foodPoints": 21,
      "tacoPoints": 23,
      "margaritaPoints": 42,
      "quesoPoints": 7,
      "burritoPoints": 88,
      "salsaPoints": 1
    },
    {
      "id": 13,
      "name": "Cafe Mineiro Bakery",
      "address": "3744 Nolensville Pike, Nashville, TN 37211",
      "hours": "shit",
      "phoneNumber": "(615) 942-6732",
      "description": "Delicious twist on Brazilian food! Stop by our bakery.",
      "establishmentTypeID": 1,
      "beer": "Yes",
      "liquor": "No",
      "mixDrinks": "No",
      "freeSalsa": "No",
      "PaymentTypeID": 3,
      "foodPoints": 3,
      "tacoPoints": 13,
      "margaritaPoints": 0,
      "quesoPoints": 0,
      "burritoPoints": 0,
      "salsaPoints": 0
    },
    {
      "id": 14,
      "name": "LA MICHOACANA PREMIUM",
      "address": "3763 Nolensville Pike, Nashville, TN 37211",
      "hours": "shit",
      "phoneNumber": "(615) 457-1385",
      "description": "We serve ice cream and treats! We love exotic flavors, do you?",
      "establishmentTypeID": 1,
      "beer": "No",
      "liquor": "No",
      "mixDrinks": "No",
      "freeSalsa": "No",
      "PaymentTypeID": 3,
      "foodPoints": 6,
      "tacoPoints": 15,
      "margaritaPoints": 12,
      "quesoPoints": 7,
      "burritoPoints": 21,
      "salsaPoints": 6
    },
    {
      "id": 15,
      "name": "Los Arcos Mexican Grill",
      "address": "3798 Nolensville Pike, Nashville, TN 37211",
      "hours": "shit",
      "phoneNumber": "(615) 837-3800",
      "description": "Come have some great food. Stay for the margaritas",
      "establishmentTypeID": 1,
      "beer": "Yes",
      "liquor": "Yes",
      "mixDrinks": "Yes",
      "freeSalsa": "Yes",
      "PaymentTypeID": 3,
      "foodPoints": 0,
      "tacoPoints": 23,
      "margaritaPoints": 43,
      "quesoPoints": 0,
      "burritoPoints": 21,
      "salsaPoints": 2
    },
    {
      "id": 16,
      "name": "Botanas Lokas",
      "address": "3955 Nolensville Pike, Nashville, TN 37211",
      "hours": "shit",
      "phoneNumber": "(615) 373-9292",
      "description": "Quick Mexican street food!",
      "establishmentTypeID": 1,
      "beer": "No",
      "liquor": "No",
      "mixDrinks": "No",
      "freeSalsa": "No",
      "PaymentTypeID": 3,
      "foodPoints": 61,
      "tacoPoints": 32,
      "margaritaPoints": 6,
      "quesoPoints": 25,
      "burritoPoints": 23,
      "salsaPoints": 2
    },
    {
      "id": 17,
      "name": "Madera Cafe",
      "address": "3955 Nolensville Pike, Nashville, TN 37211",
      "hours": "shit",
      "phoneNumber": "(615) 373-9292",
      "description": "Madera Cafe has a selection of food choices spanning the Caribbean and South America. Try the mouth watering Cuban Sandwich or enjoy some arepas.",
      "establishmentTypeID": 1,
      "beer": "Yes",
      "liquor": "Yes",
      "mixDrinks": "Yes",
      "freeSalsa": "Yes",
      "PaymentTypeID": 3,
      "foodPoints": 5,
      "tacoPoints": 4,
      "margaritaPoints": 9,
      "quesoPoints": 4,
      "burritoPoints": 4,
      "salsaPoints": 7
    },
    {
      "id": 18,
      "name": "Paletas Tocumbo",
      "address": "3955 Nolensville Pike, Nashville, TN 37211",
      "hours": "shit",
      "phoneNumber": "(615) 373-9292",
      "description": "Sample one of their many varieties of delicious home made ice cream.",
      "establishmentTypeID": 1,
      "beer": "No",
      "liquor": "No",
      "mixDrinks": "No",
      "freeSalsa": "No",
      "PaymentTypeID": 3,
      "foodPoints": 0,
      "tacoPoints": 0,
      "margaritaPoints": 0,
      "quesoPoints": 0,
      "burritoPoints": 0,
      "salsaPoints": 0
    },
    {
      "id": 19,
      "name": "Taqueria Hidalgo",
      "address": "3955 Nolensville Pike, Nashville, TN 37211",
      "hours": "shit",
      "phoneNumber": "(615) 373-9292",
      "description": "Taqueria Hidalgo has authentic Mexican tacos, burritos, pupusas,tostadas, huaraches, gorditas and quesadillas.",
      "establishmentTypeID": 1,
      "beer": "Yes",
      "liquor": "Yes",
      "mixDrinks": "Yes",
      "freeSalsa": "Yes",
      "PaymentTypeID": 3,
      "foodPoints": 9,
      "tacoPoints": 7,
      "margaritaPoints": 5,
      "quesoPoints": 8,
      "burritoPoints": 9,
      "salsaPoints": 2
    },
    {
      "id": 20,
      "name": "Tortas Ahogadas",
      "address": "3955 Nolensville Pike, Nashville, TN 37211",
      "hours": "shit",
      "phoneNumber": "(615) 373-9292",
      "description": "Tortas Ahogadas has the tortas smothered in a special sauce plus fish and shrimp tostadas.",
      "establishmentTypeID": 1,
      "beer": "No",
      "liquor": "No",
      "mixDrinks": "No",
      "freeSalsa": "No",
      "PaymentTypeID": 3,
      "foodPoints": 3,
      "tacoPoints": 2,
      "margaritaPoints": 2,
      "quesoPoints": 5,
      "burritoPoints": 5,
      "salsaPoints": 10
    },
    {
      "id": 21,
      "name": "Tres Gauchos Grill",
      "address": "3955 Nolensville Pike, Nashville, TN 37211",
      "hours": "shit",
      "phoneNumber": "(615) 373-9292",
      "description": "Tres Gauchos Grill brings steakhouse quality to the food hall setting.",
      "establishmentTypeID": 1,
      "beer": "No",
      "liquor": "No",
      "mixDrinks": "No",
      "freeSalsa": "No",
      "PaymentTypeID": 3,
      "foodPoints": 10,
      "tacoPoints": 6,
      "margaritaPoints": 13,
      "quesoPoints": 4,
      "burritoPoints": 7,
      "salsaPoints": 13
    },
    {
      "id": 22,
      "name": "Pupuseria | Salvadorena ",
      "address": "340 Welch Rd, Nashville, TN 37211",
      "hours": "shit",
      "phoneNumber": "(615) 293-0437",
      "description": "Come and get it!",
      "establishmentTypeID": 1,
      "beer": "Yes",
      "liquor": "Yes",
      "mixDrinks": "Yes",
      "freeSalsa": "Yes",
      "PaymentTypeID": 3,
      "foodPoints": 7,
      "tacoPoints": 5,
      "margaritaPoints": 15,
      "quesoPoints": 6,
      "burritoPoints": 10,
      "salsaPoints": 5
    },
    {
      "id": 23,
      "name": "Las Cazuelas | Mexican Grill",
      "address": "4114 Nolensville Pike, Nashville, TN 37211",
      "hours": "shit",
      "phoneNumber": "(615) 833-3507",
      "description": "Tacos, Fajitas, Margaritas. We got all of it!",
      "establishmentTypeID": 1,
      "beer": "Yes",
      "liquor": "Yes",
      "mixDrinks": "Yes",
      "freeSalsa": "Yes",
      "PaymentTypeID": 3,
      "foodPoints": 0,
      "tacoPoints": 0,
      "margaritaPoints": 0,
      "quesoPoints": 0,
      "burritoPoints": 0,
      "salsaPoints": 0
    },
    {
      "id": 24,
      "name": "La Cocina Dominicana",
      "address": "4407 Nolensville Pike, Nashville, TN 37211",
      "hours": "shit",
      "phoneNumber": "(615) 789-8593",
      "description": "Delicious Dominican Food!",
      "establishmentTypeID": 1,
      "beer": "Yes",
      "liquor": "No",
      "mixDrinks": "No",
      "freeSalsa": "No",
      "PaymentTypeID": 3,
      "foodPoints": 0,
      "tacoPoints": 0,
      "margaritaPoints": 0,
      "quesoPoints": 0,
      "burritoPoints": 0,
      "salsaPoints": 0
    },
    {
      "id": 25,
      "name": "Las Americas Market",
      "address": "4715 Nolensville Pike # A, Nashville, TN 37211",
      "hours": "shit",
      "phoneNumber": "(615) 315-8888",
      "description": "Latin restaurant and market!",
      "establishmentTypeID": 1,
      "beer": "Yes",
      "liquor": "Yes",
      "mixDrinks": "Yes",
      "freeSalsa": "Yes",
      "PaymentTypeID": 3,
      "foodPoints": 7,
      "tacoPoints": 5,
      "margaritaPoints": 4,
      "quesoPoints": 3,
      "burritoPoints": 4,
      "salsaPoints": 11
    },
    {
      "id": 26,
      "name": "El Tapatio",
      "address": "4801 Nolensville Pike, Nashville, TN 37211",
      "hours": "shit",
      "phoneNumber": "(615) 835-4419",
      "description": "Started as a food truck now we here! come inside!",
      "establishmentTypeID": 1,
      "beer": "Yes",
      "liquor": "No",
      "mixDrinks": "No",
      "freeSalsa": "No",
      "PaymentTypeID": 3,
      "foodPoints": 0,
      "tacoPoints": 0,
      "margaritaPoints": 0,
      "quesoPoints": 0,
      "burritoPoints": 0,
      "salsaPoints": 0
    },
    {
      "id": 27,
      "name": "La Michoacana Golden",
      "address": "4860 Nolensville Pike, Nashville, TN 37211",
      "hours": "shit",
      "phoneNumber": "(615) 732-1978",
      "description": "Doesn't get much better than this. Anything in here is good, palatas, milkshake, juice and snacks.",
      "establishmentTypeID": 1,
      "beer": "No",
      "liquor": "No",
      "mixDrinks": "No",
      "freeSalsa": "No",
      "PaymentTypeID": 3,
      "foodPoints": 10,
      "tacoPoints": 4,
      "margaritaPoints": 5,
      "quesoPoints": 14,
      "burritoPoints": 7,
      "salsaPoints": 14
    },
    {
      "id": 28,
      "name": "Panaderia La Dorada",
      "address": "4833 Nolensville Pike, Nashville, TN 37211",
      "hours": "shit",
      "phoneNumber": "(615) 833-3981",
      "description": "Come to our small bakery. We make authentic treats",
      "establishmentTypeID": 1,
      "beer": "No",
      "liquor": "No",
      "mixDrinks": "No",
      "freeSalsa": "No",
      "PaymentTypeID": 3,
      "foodPoints": 0,
      "tacoPoints": 0,
      "margaritaPoints": 0,
      "quesoPoints": 0,
      "burritoPoints": 0,
      "salsaPoints": 0
    },
    {
      "id": 29,
      "name": "Taqueria Los Gallos",
      "address": "375M+78 Nashville, Tennessee",
      "hours": "shit",
      "phoneNumber": "(615) 481-8761",
      "description": "Small taco truck, bug flavor!",
      "establishmentTypeID": 2,
      "beer": "Yes",
      "liquor": "No",
      "mixDrinks": "No",
      "freeSalsa": "No",
      "PaymentTypeID": 1,
      "foodPoints": 1,
      "tacoPoints": 3,
      "margaritaPoints": 8,
      "quesoPoints": 4,
      "burritoPoints": 9,
      "salsaPoints": 2
    },
    {
      "id": 30,
      "name": "ELOTES NAYARIT & TAQUERIA",
      "address": "5111 Nolensville Pike, Nashville, TN 37211",
      "hours": "shit",
      "phoneNumber": "(615) 394-8897",
      "description": "Fast Hispanic food!",
      "establishmentTypeID": 1,
      "beer": "Yes",
      "liquor": "No",
      "mixDrinks": "No",
      "freeSalsa": "No",
      "PaymentTypeID": 3,
      "foodPoints": 0,
      "tacoPoints": 0,
      "margaritaPoints": 0,
      "quesoPoints": 0,
      "burritoPoints": 0,
      "salsaPoints": 0
    },
    {
      "id": 31,
      "name": "Pupuseria Salvadorena Santa Rosa",
      "address": "5122 Nolensville Pike, Nashville, TN 37211",
      "hours": "shit",
      "phoneNumber": "(615) 730-5177",
      "description": "Small but we have in door seating!",
      "establishmentTypeID": 1,
      "beer": "Yes",
      "liquor": "No",
      "mixDrinks": "No",
      "freeSalsa": "No",
      "PaymentTypeID": 3,
      "foodPoints": 6,
      "tacoPoints": 14,
      "margaritaPoints": 4,
      "quesoPoints": 7,
      "burritoPoints": 6,
      "salsaPoints": 4
    },
    {
      "id": 32,
      "name": "tortas gigantes jalisco",
      "address": "5130 Nolensville Pike, Nashville, TN 37211",
      "hours": "shit",
      "phoneNumber": "(615) 416-9194",
      "description": "Food truck foodin!",
      "establishmentTypeID": 1,
      "beer": "No",
      "liquor": "No",
      "mixDrinks": "No",
      "freeSalsa": "No",
      "PaymentTypeID": 1,
      "foodPoints": 7,
      "tacoPoints": 11,
      "margaritaPoints": 10,
      "quesoPoints": 7,
      "burritoPoints": 7,
      "salsaPoints": 5
    },
    {
      "id": 33,
      "name": "La Cocina Dominicana",
      "address": "La Cocina Dominicana",
      "hours": "shit",
      "phoneNumber": "(615) 789-8593",
      "description": "Delicious Dominican Food!",
      "establishmentTypeID": 1,
      "beer": "Yes",
      "liquor": "No",
      "mixDrinks": "No",
      "freeSalsa": "No",
      "PaymentTypeID": 3,
      "foodPoints": 16,
      "tacoPoints": 8,
      "margaritaPoints": 8,
      "quesoPoints": 5,
      "burritoPoints": 8,
      "salsaPoints": 9
    },
    {
      "id": 34,
      "name": "Michoacana",
      "address": "5207 Nolensville Pike, Nashville, TN 37211",
      "hours": "shit",
      "phoneNumber": "(615) 953-2470",
      "description": "Delicious sit down restaurant!",
      "establishmentTypeID": 1,
      "beer": "Yes",
      "liquor": "Yes",
      "mixDrinks": "Yes",
      "freeSalsa": "Yes",
      "PaymentTypeID": 3,
      "foodPoints": 11,
      "tacoPoints": 4,
      "margaritaPoints": 2,
      "quesoPoints": 5,
      "burritoPoints": 6,
      "salsaPoints": 15
    },
    {
      "id": 35,
      "name": "Tacos Lopez",
      "address": "5414 Nolensville Pike, Nashville, TN 37211",
      "hours": "shit",
      "phoneNumber": "(615) 833-0336",
      "description": "Taco Truck! Cheap prices, great food",
      "establishmentTypeID": 2,
      "beer": "Yes",
      "liquor": "No",
      "mixDrinks": "No",
      "freeSalsa": "No",
      "PaymentTypeID": 1,
      "foodPoints": 7,
      "tacoPoints": 7,
      "margaritaPoints": 6,
      "quesoPoints": 5,
      "burritoPoints": 6,
      "salsaPoints": 6
    },
    {
      "id": 36,
      "name": "La Terraza",
      "address": "5751 Nolensville Pike, Nashville, TN 37211",
      "hours": "shit",
      "phoneNumber": "(615) 835-0106",
      "description": "Your normal Mexican style restaurant!",
      "establishmentTypeID": 1,
      "beer": "Yes",
      "liquor": "Yes",
      "mixDrinks": "Yes",
      "freeSalsa": "Yes",
      "PaymentTypeID": 3,
      "foodPoints": 5,
      "tacoPoints": 5,
      "margaritaPoints": 11,
      "quesoPoints": 5,
      "burritoPoints": 5,
      "salsaPoints": 6
    },
    {
      "id": 37,
      "name": "Fogatas Authentic Mexican Food",
      "address": "5560 Nolensville Pike, Nashville, TN 37211",
      "hours": "shit",
      "phoneNumber": "(615) 331-6281",
      "description": "Authentic Mexican Food!",
      "establishmentTypeID": 1,
      "beer": "Yes",
      "liquor": "Yes",
      "mixDrinks": "Yes",
      "freeSalsa": "Yes",
      "PaymentTypeID": 3,
      "foodPoints": 9,
      "tacoPoints": 6,
      "margaritaPoints": 4,
      "quesoPoints": 6,
      "burritoPoints": 4,
      "salsaPoints": 7
    },
    {
      "id": 38,
      "name": "EL SOMBRERO MEXICAN RESTAURANT",
      "address": "6017 Nolensville Pike, Nashville, TN 37211",
      "hours": "shit",
      "phoneNumber": "(615) 445-8758",
      "description": "Delicious Mexican style family restaurant",
      "establishmentTypeID": 1,
      "beer": "Yes",
      "liquor": "Yes",
      "mixDrinks": "Yes",
      "freeSalsa": "Yes",
      "PaymentTypeID": 3,
      "foodPoints": 3,
      "tacoPoints": 7,
      "margaritaPoints": 21,
      "quesoPoints": 9,
      "burritoPoints": 0,
      "salsaPoints": 4
    },
    {
      "id": 39,
      "name": "Los Portales Mexican Restaurant",
      "address": "4605, 6448 Nolensville Pike, Antioch, TN 37013",
      "hours": "shit",
      "phoneNumber": "(615) 283-6180",
      "description": "mmmmmmmMexican food!",
      "establishmentTypeID": 1,
      "beer": "Yes",
      "liquor": "Yes",
      "mixDrinks": "Yes",
      "freeSalsa": "Yes",
      "PaymentTypeID": 3,
      "foodPoints": 7,
      "tacoPoints": 7,
      "margaritaPoints": 12,
      "quesoPoints": 10,
      "burritoPoints": 7,
      "salsaPoints": 6
    },
    {
      "id": 40,
      "name": "Las Palmas Mexican Restaurant",
      "address": "6688 Nolensville Rd, Brentwood, TN 37027",
      "hours": "shit",
      "phoneNumber": "(615) 941-4756",
      "description": "Let's taco bout it",
      "establishmentTypeID": 1,
      "beer": "Yes",
      "liquor": "Yes",
      "mixDrinks": "Yes",
      "freeSalsa": "Yes",
      "PaymentTypeID": 3,
      "foodPoints": 0,
      "tacoPoints": 0,
      "margaritaPoints": 0,
      "quesoPoints": 0,
      "burritoPoints": 0,
      "salsaPoints": 0
    },
    {
      "id": 41,
      "name": "Campo Azul",
      "address": "7240 Nolensville Rd #105, Nolensville, TN 37135",
      "hours": "shit",
      "phoneNumber": "(615) 776-1570",
      "description": "Best Mexican food in Franklin!",
      "establishmentTypeID": 1,
      "beer": "Yes",
      "liquor": "Yes",
      "mixDrinks": "Yes",
      "freeSalsa": "Yes",
      "PaymentTypeID": 3,
      "foodPoints": 0,
      "tacoPoints": 0,
      "margaritaPoints": 0,
      "quesoPoints": 0,
      "burritoPoints": 0,
      "salsaPoints": 0
    }
  ],
  "messages": [
    {
      "username": "moon",
      "message": "bllop",
      "date": 1536871594487,
      "establishmentID": 1,
      "id": 11
    },
    {
      "username": "meow",
      "message": "i hated it!",
      "date": 1536871734756,
      "establishmentID": 1,
      "id": 13
    },
    {
      "username": "meow",
      "message": "bloop",
      "date": 1536872845963,
      "establishmentID": 5,
      "id": 14
    },
    {
      "username": "meow",
      "message": "2",
      "date": "",
      "establishmentID": 1,
      "id": 15
    },
    {
      "username": "moon",
      "message": "today was living hell",
      "date": 1536957347269,
      "establishmentID": 1,
      "id": 17
    },
    {
      "username": "moon",
      "message": "zing!!!",
      "date": 1537286351334,
      "establishmentID": 3,
      "id": 21
    },
    {
      "username": "moon",
      "message": "zinfg",
      "date": 1537294496872,
      "establishmentID": 3,
      "id": 23
    },
    {
      "username": "moon",
      "message": "hiya",
      "date": 1537294504922,
      "establishmentID": 3,
      "id": 24
    },
    {
      "username": "moon",
      "message": "bloop",
      "date": 1537294514502,
      "establishmentID": 3,
      "id": 25
    },
    {
      "username": "moon",
      "message": "bloopasdfsdf!!!!!2323 meow skjbnfsdkjsf chicken",
      "date": 1537294753443,
      "establishmentID": 2,
      "id": 26
    },
    {
      "username": "joden",
      "message": "big yum yummer",
      "date": 1537300925811,
      "establishmentID": 1,
      "id": 27
    },
    {
      "username": "moonmoon",
      "message": "God save the childrens",
      "date": 1537322981597,
      "establishmentID": 1,
      "id": 28
    },
    {
      "username": "moonmoon",
      "message": "Authentic and tasty treats!",
      "date": 1537323009897,
      "establishmentID": 4,
      "id": 29
    },
    {
      "username": "moonmoon",
      "message": "I love Dejan more than any other man in the wooooooooorld.",
      "date": 1537323042866,
      "establishmentID": 7,
      "id": 30
    },
    {
      "username": "1",
      "message": "bloop",
      "date": 1537366726136,
      "establishmentID": 2,
      "id": 31
    },
    {
      "username": "moon",
      "message": "",
      "date": 1537383988308,
      "establishmentID": 2,
      "id": 32
    },
    {
      "username": "dingdong69",
      "message": "something cool",
      "date": 1537384360796,
      "establishmentID": 5,
      "id": 33
    },
    {
      "username": "dingdong69",
      "message": "White space at bottom issue\nShouldn't be able to edit or delete other user's messages",
      "date": 1537384550898,
      "establishmentID": 2,
      "id": 34
    },
    {
      "username": "brett",
      "message": "DEJAN IS WHITE",
      "date": 1537384916015,
      "establishmentID": 7,
      "id": 35
    },
    {
      "username": "brett",
      "message": "laskjdfa;dlkfj",
      "date": 1537384947145,
      "establishmentID": 5,
      "id": 36
    },
    {
      "username": "brett",
      "message": "ghfhgfhf",
      "date": 1537385004457,
      "establishmentID": 1,
      "id": 37
    },
    {
      "username": "brett",
      "message": "",
      "date": "",
      "establishmentID": 3,
      "id": 38
    },
    {
      "username": "brett",
      "message": "hghghg",
      "date": 1537385085281,
      "establishmentID": 7,
      "id": 39
    },
    {
      "username": "brett",
      "message": "bloop",
      "date": 1537385303208,
      "establishmentID": 3,
      "id": 40
    },
    {
      "username": "brett",
      "message": "dfgvfds",
      "date": 1537385327458,
      "establishmentID": 1,
      "id": 41
    },
    {
      "username": "brett",
      "message": "Fix the issue where when you delete a message and try to post a new message, the screen goes blank.  XOXOXO - Breezy",
      "date": 1537385654051,
      "establishmentID": 2,
      "id": 42
    },
    {
      "username": "urbutt",
      "message": "pneumonoultramicroscopicsilicovolcaniconiosis",
      "date": 1537385849453,
      "establishmentID": 1,
      "id": 43
    },
    {
      "username": "urbutt",
      "message": "white on yellow is a bit hard on the eyes.  when you try to edit a second time the text you're trying to edit does not show up.  styling, though honestly there is a minimalist aesthetic that i like so far.  maybe differentiate the user name from the post a bit more, or even put the user name below the post.  damn bro you don't have to write a god damned book. shit",
      "date": 1537386122251,
      "establishmentID": 2,
      "id": 44
    },
    {
      "username": "al",
      "message": "Dude the torta and coke here was immaculate. The avacados reminded me of sex.",
      "date": 1537386365845,
      "establishmentID": 5,
      "id": 45
    },
    {
      "username": "moon",
      "message": "see if you can make messages take up 50% VW and 100%VH, then throw a scroll in that mug!",
      "date": 1537387466386,
      "establishmentID": 2,
      "id": 46
    },
    {
      "username": "megducharme",
      "message": "woo!",
      "date": 1537390827547,
      "establishmentID": 8,
      "id": 47
    },
    {
      "username": "moon",
      "message": "dasfsadf",
      "date": 1537391248792,
      "establishmentID": 2,
      "id": 48
    },
    {
      "username": "moon",
      "message": "bloop",
      "date": 1537392052985,
      "establishmentID": 8,
      "id": 49
    },
    {
      "username": "moon",
      "message": "meow",
      "date": 1537392057000,
      "establishmentID": 8,
      "id": 50
    },
    {
      "username": "moon",
      "message": "izoom",
      "date": 1537393673055,
      "establishmentID": 8,
      "id": 51
    },
    {
      "username": "moon",
      "message": "new message",
      "date": 1537394853409,
      "establishmentID": 2,
      "id": 52
    },
    {
      "username": "moon",
      "message": "meow!",
      "date": 1537394944870,
      "establishmentID": 2,
      "id": 53
    },
    {
      "username": "moon",
      "message": "",
      "date": 1537395032531,
      "establishmentID": 1,
      "id": 54
    },
    {
      "username": "moon",
      "message": "dfgds",
      "date": 1537395065423,
      "establishmentID": 2,
      "id": 55
    },
    {
      "username": "moon",
      "message": "sf",
      "date": 1537395147280,
      "establishmentID": 2,
      "id": 56
    },
    {
      "username": "moon",
      "message": "meow!",
      "date": 1537395176572,
      "establishmentID": 2,
      "id": 57
    },
    {
      "username": "moon",
      "message": "message!!",
      "date": 1537395365633,
      "establishmentID": 2,
      "id": 58
    },
    {
      "username": "moon",
      "message": "!",
      "date": 1537395476677,
      "establishmentID": 2,
      "id": 59
    },
    {
      "username": "moon",
      "message": "fsag!",
      "date": 1537395480530,
      "establishmentID": 2,
      "id": 60
    },
    {
      "username": "jennabsol",
      "message": "hello",
      "date": 1537396731839,
      "establishmentID": 8,
      "id": 61
    },
    {
      "username": "moonl",
      "message": "boop",
      "date": 1537406954307,
      "establishmentID": 13,
      "id": 62
    },
    {
      "username": "moonl",
      "message": "yaaaaas",
      "date": 1537406984044,
      "establishmentID": 4,
      "id": 63
    },
    {
      "username": "moonl",
      "message": "sdfsdfs!!",
      "date": 1537407271283,
      "establishmentID": 2,
      "id": 64
    },
    {
      "username": "moon",
      "message": "meow",
      "date": 1537453227671,
      "establishmentID": 3,
      "id": 66
    },
    {
      "username": "moon",
      "message": "zoom ",
      "date": 1537453240290,
      "establishmentID": 2,
      "id": 67
    },
    {
      "username": "moon",
      "message": "sdfsdf",
      "date": 1537453457869,
      "establishmentID": 1,
      "id": 68
    },
    {
      "username": "moon",
      "message": "dsf ssss bloop meow ",
      "date": 1537453489951,
      "establishmentID": 1,
      "id": 69
    },
    {
      "username": "moon",
      "message": "moon",
      "date": 1537456849599,
      "establishmentID": 3,
      "id": 71
    },
    {
      "username": "moon",
      "message": "meow",
      "date": 1537457016274,
      "establishmentID": 3,
      "id": 72
    },
    {
      "username": "moon",
      "message": "Hi Dejan, you have that poppin booty",
      "date": 1537551040515,
      "establishmentID": 2,
      "id": 73
    },
    {
      "username": "janjan",
      "message": "I personally liked the ambiance of the restaurant. The dim lighting and the quite, but peaceful music really set the mood for my sacred ritual of consuming and masticating my food. This sacred ritual is something that must be carefully planned and executed. If one thing goes wrong, I could projectile vomit all the food I just consumed, and thus, be left hungry and weak. This restaurant definitely provided the necessary requirements for my needs. Definite thumbs up, bro!     ",
      "date": 1538078649116,
      "establishmentID": 5,
      "id": 74
    },
    {
      "username": "banksmoon",
      "message": "boopbopp",
      "date": 1538141351182,
      "establishmentID": 2,
      "id": 75
    },
    {
      "username": "megducharme13",
      "message": "This place is the 💣!",
      "date": 1538145971294,
      "establishmentID": 1,
      "id": 76
    },
    {
      "username": "",
      "message": "i love tacos",
      "date": 1538251409167,
      "establishmentID": 1,
      "id": 77
    },
    {
      "username": "dingdong420",
      "message": "KOOOOOOOL\n\n",
      "date": 1538255788490,
      "establishmentID": 3,
      "id": 78
    },
    {
      "username": "moon",
      "message": "",
      "date": "",
      "establishmentID": 4,
      "id": 79
    },
    {
      "username": "moon",
      "message": "bloop",
      "date": 1538410004949,
      "establishmentID": 4,
      "id": 80
    },
    {
      "username": "moon",
      "message": "sooooo yummy! I cant believe my taste buds",
      "date": 1538411164242,
      "establishmentID": 2,
      "id": 82
    },
    {
      "username": "moon",
      "message": "wooooow sooo good",
      "date": 1538418972299,
      "establishmentID": 1,
      "id": 83
    },
    {
      "username": "moon",
      "message": "zing!!!",
      "date": 1538419049149,
      "establishmentID": 4,
      "id": 84
    },
    {
      "username": "moon",
      "message": "I thought it was ok. Nothing special",
      "date": 1538434093822,
      "establishmentID": 6,
      "id": 85
    },
    {
      "username": "moon",
      "message": "Dreaming of eating here again!\n",
      "date": 1538434109932,
      "establishmentID": 36,
      "id": 86
    },
    {
      "username": "moon",
      "message": "WOooow the Pupusa's here are🔥",
      "date": 1538434168090,
      "establishmentID": 10,
      "id": 87
    }
  ],
  "establishmentType": [
    {
      "id": 1,
      "type": "Restaurant"
    },
    {
      "id": 2,
      "type": "Food Truck"
    }
  ],
  "paymentType": [
    {
      "id": 1,
      "type": "Cash"
    },
    {
      "id": 2,
      "type": "Credit/Debit Cards"
    },
    {
      "id": 3,
      "type": "Cash or Credit/Debit Cards"
    }
  ],
  "categories": [
    {
      "name": "Food",
      "establishmentID": 2,
      "vote": 0,
      "id": 1
    }
  ]
}